asyncpg_lock/__init__.py
asyncpg_lock/guard.py
asyncpg_lock/py.typed
asyncpg_lock-0.0.1.dist-info/LICENSE
asyncpg_lock-0.0.1.dist-info/METADATA
asyncpg_lock-0.0.1.dist-info/WHEEL
asyncpg_lock-0.0.1.dist-info/top_level.txt
asyncpg_lock-0.0.1.dist-info/RECORD
